bluebrick/__init__.py
bluebrick/ble_queue.py
bluebrick/bluebrick.py
bluebrick/const.py
bluebrick/hub.py
bluebrick/messages.py
bluebrick/peripheral.py
bluebrick/process.py
bluebrick/sensor.py
bluebrick/utils.py
bluebrick/version.py
bricknil/__init__.py
bricknil/ble_queue.py
bricknil/bleak.py
bricknil/bleak_interface.py
bricknil/bricknil.py
bricknil/const.py
bricknil/hub.py
bricknil/message_dispatch.py
bricknil/messages.py
bricknil/peripheral.py
bricknil/process.py
bricknil/sensor.py
bricknil/sockets.py
bricknil/utils.py
bricknil/version.py
bricknil/sensor/__init__.py
bricknil/sensor/light.py
bricknil/sensor/motor.py
bricknil/sensor/peripheral.py
bricknil/sensor/sensor.py
bricknil/sensor/sound.py
bricknil-0.9.3.dist-info/LICENSE.txt
bricknil-0.9.3.dist-info/METADATA
bricknil-0.9.3.dist-info/WHEEL
bricknil-0.9.3.dist-info/entry_points.txt
bricknil-0.9.3.dist-info/top_level.txt
bricknil-0.9.3.dist-info/zip-safe
bricknil-0.9.3.dist-info/RECORD
