Metadata-Version: 2.1
Name: bricknil
Version: 0.9.3
Summary: Control LEGO(tm) BluetoothLE Hubs, Motors, and Sensors using Async Python
Home-page: https://virantha.github.io/bricknil
Author: Virantha N. Ekanayake
Author-email: virantha@gmail.com
License: ASL 2.0
Platform: UNKNOWN
Requires-Dist: pyyaml
Requires-Dist: curio
Requires-Dist: bluebrick-Adafruit-BluefruitLE (>=0.9.12)
Requires-Dist: bricknil-bleak ; sys_platform != "darwin"
Requires-Dist: pyobjc ; sys_platform == "darwin"
